<?xml version="1.0" encoding="utf-8" ?>
<dwsync>
<file name="direita.png" server="C:/apache2triad/htdocs/" local="129272550300000000" remote="129272550300000000" />
<file name="jogosbotao.jpg" server="C:/apache2triad/htdocs/" local="129286442967127923" remote="129286442960000000" />
<file name="portal.jpg" server="C:/apache2triad/htdocs/" local="129286442426807018" remote="129286442420000000" />
<file name="bg.png" server="C:/apache2triad/htdocs/myiconelocal/" local="129270720780000000" remote="129270720780000000" />
<file name="artetoposite.jpg" server="C:/apache2triad/htdocs/myiconelocal/" local="129282642473694613" remote="129282642470000000" />
<file name="direita.png" server="C:/apache2triad/htdocs/myiconelocal/" local="129272550300000000" remote="129272550300000000" />
<file name="cm.jpg" server="C:/apache2triad/htdocs/myiconelocal/" local="129300976494432610" remote="129300976490000000" />
<file name="jogosbotao.jpg" server="C:/apache2triad/htdocs/myiconelocal/" local="129286442967127923" remote="129286442960000000" />
<file name="portal.jpg" server="C:/apache2triad/htdocs/myiconelocal/" local="129286442426807018" remote="129286442420000000" />
<file name="ct.jpg" server="C:/apache2triad/htdocs/myiconelocal/" local="129300975683715594" remote="129300975680000000" />
<file name="indicadoresbotao.jpg" server="C:/apache2triad/htdocs/myiconelocal/" local="129301063515477909" remote="129301063510000000" />
<file name="esquerda.png" server="C:/apache2triad/htdocs/myiconelocal/" local="129272550380000000" remote="129272550380000000" />
<file name="bg.png" server="C:/apache2triad/htdocs/myiconecom/" local="129379480574273704" remote="129379480570000000" />
<file name="artetoposite.jpg" server="C:/apache2triad/htdocs/myiconecom/" local="129380403248757950" remote="129380403240000000" />
<file name="direita.png" server="C:/apache2triad/htdocs/myiconecom/" local="129379480443776240" remote="129379480440000000" />
<file name="jogosbotao.jpg" server="C:/apache2triad/htdocs/myiconecom/" local="129379480560482915" remote="129379480560000000" />
<file name="indicadoresbotao.jpg" server="C:/apache2triad/htdocs/myiconecom/" local="129379480470877790" remote="129379480470000000" />
<file name="ct.jpg" server="C:/apache2triad/htdocs/myiconecom/" local="129379480538101635" remote="129379480530000000" />
<file name="cm.jpg" server="C:/apache2triad/htdocs/myiconecom/" local="129379480543631952" remote="129379480540000000" />
<file name="banner.png" server="C:/apache2triad/htdocs/myiconecom/" local="129379561778021796" remote="129379561770000000" />
<file name="banner2.png" server="C:/apache2triad/htdocs/myiconecom/" local="129381203177328198" remote="129381203170000000" />
<file name="logonovo.jpg" server="C:/apache2triad/htdocs/myiconecom/" local="129381226092948897" remote="129381226090000000" />
<file name="seta2.png" server="C:/apache2triad/htdocs/myiconecom/" local="129381219891254180" remote="129381219890000000" />
<file name="2.png" server="C:/apache2triad/htdocs/myiconecom/" local="129381212001492912" remote="129381212000000000" />
<file name="ctnovo.png" server="C:/apache2triad/htdocs/myiconecom/" local="129381228290654598" remote="129381228290000000" />
<file name="cmnovo.png" server="C:/apache2triad/htdocs/myiconecom/" local="129381228007058378" remote="129381228000000000" />
<file name="1.png" server="C:/apache2triad/htdocs/myiconecom/" local="129381246515717012" remote="129381246510000000" />
<file name="seta1.png" server="C:/apache2triad/htdocs/myiconecom/" local="129381220079644955" remote="129381220070000000" />
<file name="games.png" server="C:/apache2triad/htdocs/myiconecom/" local="129381235179938643" remote="129381235170000000" />
<file name="indice.png" server="C:/apache2triad/htdocs/myiconecom/" local="129381235466665043" remote="129381235460000000" />
<file name="bg.png" server="C:/apache2triad/htdocs/myiconebr/" local="129385791459265250" remote="129385791450000000" />
<file name="banner.png" server="C:/apache2triad/htdocs/myiconebr/" local="129379561778021796" remote="129379561770000000" />
<file name="games.png" server="C:/apache2triad/htdocs/myiconebr/" local="129385791395241588" remote="129385791390000000" />
<file name="indice.png" server="C:/apache2triad/htdocs/myiconebr/" local="129385791431923686" remote="129385791430000000" />
<file name="1.png" server="C:/apache2triad/htdocs/myiconebr/" local="129385791496497380" remote="129385791490000000" />
<file name="seta1.png" server="C:/apache2triad/htdocs/myiconebr/" local="129385791486936833" remote="129385791480000000" />
<file name="ctnovo.png" server="C:/apache2triad/htdocs/myiconebr/" local="129385791409842423" remote="129385791400000000" />
<file name="cmnovo.png" server="C:/apache2triad/htdocs/myiconebr/" local="129385791427703445" remote="129385791420000000" />
<file name="logonovo.jpg" server="C:/apache2triad/htdocs/myiconebr/" local="129385791403412056" remote="129385791400000000" />
</dwsync>